{
  "id": 27,
  "name": "Alaska_Anchorage_East",
  "description": "Alaska_Anchorage_East",
  "type": "work",
  "places": [
    {
      "placeId": "ChIJjXJ229mXyFYRN9Bs-plBkds",
      "distance": 94,
      "duration": 8.999999999999986,
      "speedLimit": 35
    },
    {
      "placeId": "ChIJV7XB89mXyFYRwgBkXnyRXKM",
      "distance": 13,
      "duration": 0.9999999999999998,
      "speedLimit": 35
    },
    {
      "placeId": "ChIJl_my6NmXyFYRcFzQcMV8Uvs",
      "distance": 46,
      "duration": 4.000000000000003,
      "speedLimit": 35
    },
    {
      "placeId": "ChIJuUyQ29mXyFYRwrEiHgAGkDM",
      "distance": 1,
      "duration": 0.0,
      "speedLimit": 35
    },
    {
      "placeId": "ChIJlc0f8tmXyFYRQh-fvkjtpTA",
      "distance": 76,
      "duration": 11.000000000000007,
      "speedLimit": 35
    },
    {
      "placeId": "ChIJPwjp89mXyFYRctQOXm4JkYM",
      "distance": 4,
      "duration": 0.0,
      "speedLimit": 35
    }
  ],
  "segments": [
    {
      "startLocation": {
        "lat": 61.200286,
        "lng": -149.9077844
      },
      "endLocation": {
        "lat": 61.200286,
        "lng": -149.9077844
      },
      "distance": 0,
      "duration": 0,
      "points": [
        {
          "lat": 61.20028591917681,
          "lng": -149.9077840911278,
          "placeId": "ChIJuUyQ29mXyFYRwrEiHgAGkDM"
        }
      ]
    },
    {
      "startLocation": {
        "lat": 61.200286,
        "lng": -149.9077844
      },
      "endLocation": {
        "lat": 61.2001904,
        "lng": -149.9077079
      },
      "distance": 11,
      "duration": 1,
      "points": [
        {
          "lat": 61.20028593531311,
          "lng": -149.90778434822354,
          "placeId": "ChIJjXJ229mXyFYRN9Bs-plBkds"
        },
        {
          "lat": 61.20027696826208,
          "lng": -149.90777717085209,
          "placeId": "ChIJjXJ229mXyFYRN9Bs-plBkds"
        },
        {
          "lat": 61.2002688717694,
          "lng": -149.9077706902932,
          "placeId": "ChIJjXJ229mXyFYRN9Bs-plBkds"
        },
        {
          "lat": 61.200260066434275,
          "lng": -149.90776364236987,
          "placeId": "ChIJjXJ229mXyFYRN9Bs-plBkds"
        },
        {
          "lat": 61.200251099381184,
          "lng": -149.9077564650094,
          "placeId": "ChIJjXJ229mXyFYRN9Bs-plBkds"
        },
        {
          "lat": 61.200243002886666,
          "lng": -149.90774998446048,
          "placeId": "ChIJjXJ229mXyFYRN9Bs-plBkds"
        },
        {
          "lat": 61.20023403583224,
          "lng": -149.90774280710733,
          "placeId": "ChIJjXJ229mXyFYRN9Bs-plBkds"
        },
        {
          "lat": 61.2002250687771,
          "lng": -149.90773562975792,
          "placeId": "ChIJjXJ229mXyFYRN9Bs-plBkds"
        },
        {
          "lat": 61.200216101721225,
          "lng": -149.90772845241236,
          "placeId": "ChIJjXJ229mXyFYRN9Bs-plBkds"
        },
        {
          "lat": 61.20020800522422,
          "lng": -149.90772197187692,
          "placeId": "ChIJjXJ229mXyFYRN9Bs-plBkds"
        },
        {
          "lat": 61.20019903816699,
          "lng": -149.90771479453863,
          "placeId": "ChIJjXJ229mXyFYRN9Bs-plBkds"
        },
        {
          "lat": 61.200190071109084,
          "lng": -149.9077076172042,
          "placeId": "ChIJjXJ229mXyFYRN9Bs-plBkds"
        }
      ]
    },
    {
      "startLocation": {
        "lat": 61.2001904,
        "lng": -149.9077079
      },
      "endLocation": {
        "lat": 61.2001693,
        "lng": -149.9076825
      },
      "distance": 3,
      "duration": 0,
      "points": [
        {
          "lat": 61.200190071109084,
          "lng": -149.9077076172042,
          "placeId": "ChIJjXJ229mXyFYRN9Bs-plBkds"
        },
        {
          "lat": 61.20018293930719,
          "lng": -149.90769921362977,
          "placeId": "ChIJjXJ229mXyFYRN9Bs-plBkds"
        },
        {
          "lat": 61.20017605924137,
          "lng": -149.90769079147913,
          "placeId": "ChIJjXJ229mXyFYRN9Bs-plBkds"
        },
        {
          "lat": 61.200169179174644,
          "lng": -149.90768236933164,
          "placeId": "ChIJjXJ229mXyFYRN9Bs-plBkds"
        }
      ]
    },
    {
      "startLocation": {
        "lat": 61.2001693,
        "lng": -149.9076825
      },
      "endLocation": {
        "lat": 61.1997016,
        "lng": -149.9066172
      },
      "distance": 77,
      "duration": 8,
      "points": [
        {
          "lat": 61.200169179174644,
          "lng": -149.90768236933164,
          "placeId": "ChIJjXJ229mXyFYRN9Bs-plBkds"
        },
        {
          "lat": 61.20016239669158,
          "lng": -149.90767013760194,
          "placeId": "ChIJjXJ229mXyFYRN9Bs-plBkds"
        },
        {
          "lat": 61.20015632728869,
          "lng": -149.90765626846874,
          "placeId": "ChIJjXJ229mXyFYRN9Bs-plBkds"
        },
        {
          "lat": 61.200150257883756,
          "lng": -149.9076423993395,
          "placeId": "ChIJjXJ229mXyFYRN9Bs-plBkds"
        },
        {
          "lat": 61.20014418847676,
          "lng": -149.90762853021408,
          "placeId": "ChIJjXJ229mXyFYRN9Bs-plBkds"
        },
        {
          "lat": 61.20013811906774,
          "lng": -149.90761466109265,
          "placeId": "ChIJjXJ229mXyFYRN9Bs-plBkds"
        },
        {
          "lat": 61.20013204965667,
          "lng": -149.9076007919751,
          "placeId": "ChIJjXJ229mXyFYRN9Bs-plBkds"
        },
        {
          "lat": 61.20012622001198,
          "lng": -149.9075874707521,
          "placeId": "ChIJjXJ229mXyFYRN9Bs-plBkds"
        },
        {
          "lat": 61.200120150596874,
          "lng": -149.90757360164218,
          "placeId": "ChIJjXJ229mXyFYRN9Bs-plBkds"
        },
        {
          "lat": 61.20011408117973,
          "lng": -149.90755973253619,
          "placeId": "ChIJjXJ229mXyFYRN9Bs-plBkds"
        },
        {
          "lat": 61.20010801176055,
          "lng": -149.90754586343408,
          "placeId": "ChIJjXJ229mXyFYRN9Bs-plBkds"
        },
        {
          "lat": 61.20010149022909,
          "lng": -149.90753096122933,
          "placeId": "ChIJjXJ229mXyFYRN9Bs-plBkds"
        },
        {
          "lat": 61.2000954208056,
          "lng": -149.90751709213518,
          "placeId": "ChIJjXJ229mXyFYRN9Bs-plBkds"
        },
        {
          "lat": 61.200089591148824,
          "lng": -149.90750377093434,
          "placeId": "ChIJjXJ229mXyFYRN9Bs-plBkds"
        },
        {
          "lat": 61.20008352172132,
          "lng": -149.90748990184784,
          "placeId": "ChIJjXJ229mXyFYRN9Bs-plBkds"
        },
        {
          "lat": 61.20007745229175,
          "lng": -149.90747603276526,
          "placeId": "ChIJjXJ229mXyFYRN9Bs-plBkds"
        },
        {
          "lat": 61.20007138286016,
          "lng": -149.90746216368663,
          "placeId": "ChIJjXJ229mXyFYRN9Bs-plBkds"
        },
        {
          "lat": 61.200065313426514,
          "lng": -149.90744829461187,
          "placeId": "ChIJjXJ229mXyFYRN9Bs-plBkds"
        },
        {
          "lat": 61.20005924399082,
          "lng": -149.90743442554106,
          "placeId": "ChIJjXJ229mXyFYRN9Bs-plBkds"
        },
        {
          "lat": 61.200053414322184,
          "lng": -149.90742110436221,
          "placeId": "ChIJjXJ229mXyFYRN9Bs-plBkds"
        },
        {
          "lat": 61.20004734488247,
          "lng": -149.907407235299,
          "placeId": "ChIJjXJ229mXyFYRN9Bs-plBkds"
        },
        {
          "lat": 61.2000412754407,
          "lng": -149.9073933662397,
          "placeId": "ChIJjXJ229mXyFYRN9Bs-plBkds"
        },
        {
          "lat": 61.20003520599689,
          "lng": -149.9073794971843,
          "placeId": "ChIJjXJ229mXyFYRN9Bs-plBkds"
        },
        {
          "lat": 61.200029136551045,
          "lng": -149.90736562813282,
          "placeId": "ChIJjXJ229mXyFYRN9Bs-plBkds"
        },
        {
          "lat": 61.20002306710316,
          "lng": -149.9073517590853,
          "placeId": "ChIJjXJ229mXyFYRN9Bs-plBkds"
        },
        {
          "lat": 61.200016785309465,
          "lng": -149.90733740482403,
          "placeId": "ChIJjXJ229mXyFYRN9Bs-plBkds"
        },
        {
          "lat": 61.200010715857324,
          "lng": -149.90732353578423,
          "placeId": "ChIJjXJ229mXyFYRN9Bs-plBkds"
        },
        {
          "lat": 61.20000464640315,
          "lng": -149.90730966674838,
          "placeId": "ChIJjXJ229mXyFYRN9Bs-plBkds"
        },
        {
          "lat": 61.199998576946925,
          "lng": -149.9072957977164,
          "placeId": "ChIJjXJ229mXyFYRN9Bs-plBkds"
        },
        {
          "lat": 61.19999250748866,
          "lng": -149.90728192868838,
          "placeId": "ChIJjXJ229mXyFYRN9Bs-plBkds"
        },
        {
          "lat": 61.19998643802835,
          "lng": -149.90726805966423,
          "placeId": "ChIJjXJ229mXyFYRN9Bs-plBkds"
        },
        {
          "lat": 61.19998060833576,
          "lng": -149.90725473852956,
          "placeId": "ChIJjXJ229mXyFYRN9Bs-plBkds"
        },
        {
          "lat": 61.19997453887143,
          "lng": -149.90724086951306,
          "placeId": "ChIJjXJ229mXyFYRN9Bs-plBkds"
        },
        {
          "lat": 61.19996846940505,
          "lng": -149.90722700050046,
          "placeId": "ChIJjXJ229mXyFYRN9Bs-plBkds"
        },
        {
          "lat": 61.19996239993661,
          "lng": -149.90721313149177,
          "placeId": "ChIJjXJ229mXyFYRN9Bs-plBkds"
        },
        {
          "lat": 61.199956330466144,
          "lng": -149.907199262487,
          "placeId": "ChIJjXJ229mXyFYRN9Bs-plBkds"
        },
        {
          "lat": 61.19995026099364,
          "lng": -149.90718539348615,
          "placeId": "ChIJjXJ229mXyFYRN9Bs-plBkds"
        },
        {
          "lat": 61.199944431289175,
          "lng": -149.9071720723735,
          "placeId": "ChIJjXJ229mXyFYRN9Bs-plBkds"
        },
        {
          "lat": 61.19993790969672,
          "lng": -149.9071571702779,
          "placeId": "ChIJjXJ229mXyFYRN9Bs-plBkds"
        },
        {
          "lat": 61.19993184021791,
          "lng": -149.90714330128873,
          "placeId": "ChIJjXJ229mXyFYRN9Bs-plBkds"
        },
        {
          "lat": 61.19992577073707,
          "lng": -149.90712943230346,
          "placeId": "ChIJjXJ229mXyFYRN9Bs-plBkds"
        },
        {
          "lat": 61.199919701254174,
          "lng": -149.90711556332215,
          "placeId": "ChIJjXJ229mXyFYRN9Bs-plBkds"
        },
        {
          "lat": 61.199913631769256,
          "lng": -149.90710169434473,
          "placeId": "ChIJjXJ229mXyFYRN9Bs-plBkds"
        },
        {
          "lat": 61.19990780205272,
          "lng": -149.90708837325423,
          "placeId": "ChIJjXJ229mXyFYRN9Bs-plBkds"
        },
        {
          "lat": 61.19990173256377,
          "lng": -149.9070745042844,
          "placeId": "ChIJjXJ229mXyFYRN9Bs-plBkds"
        },
        {
          "lat": 61.199895663072766,
          "lng": -149.90706063531852,
          "placeId": "ChIJjXJ229mXyFYRN9Bs-plBkds"
        },
        {
          "lat": 61.19988959357973,
          "lng": -149.90704676635656,
          "placeId": "ChIJjXJ229mXyFYRN9Bs-plBkds"
        },
        {
          "lat": 61.19988352408462,
          "lng": -149.90703289739844,
          "placeId": "ChIJjXJ229mXyFYRN9Bs-plBkds"
        },
        {
          "lat": 61.19987745458749,
          "lng": -149.90701902844432,
          "placeId": "ChIJjXJ229mXyFYRN9Bs-plBkds"
        },
        {
          "lat": 61.199871624859085,
          "lng": -149.90700570737582,
          "placeId": "ChIJjXJ229mXyFYRN9Bs-plBkds"
        },
        {
          "lat": 61.199865555357924,
          "lng": -149.9069918384293,
          "placeId": "ChIJjXJ229mXyFYRN9Bs-plBkds"
        },
        {
          "lat": 61.199859485854724,
          "lng": -149.9069779694867,
          "placeId": "ChIJjXJ229mXyFYRN9Bs-plBkds"
        },
        {
          "lat": 61.199852964230594,
          "lng": -149.9069630674478,
          "placeId": "ChIJjXJ229mXyFYRN9Bs-plBkds"
        },
        {
          "lat": 61.199846894723095,
          "lng": -149.9069491985132,
          "placeId": "ChIJjXJ229mXyFYRN9Bs-plBkds"
        },
        {
          "lat": 61.199840825213535,
          "lng": -149.90693532958247,
          "placeId": "ChIJjXJ229mXyFYRN9Bs-plBkds"
        },
        {
          "lat": 61.19983499547306,
          "lng": -149.90692200853613,
          "placeId": "ChIJjXJ229mXyFYRN9Bs-plBkds"
        },
        {
          "lat": 61.19982892595948,
          "lng": -149.90690813961305,
          "placeId": "ChIJjXJ229mXyFYRN9Bs-plBkds"
        },
        {
          "lat": 61.19982285644385,
          "lng": -149.9068942706938,
          "placeId": "ChIJjXJ229mXyFYRN9Bs-plBkds"
        },
        {
          "lat": 61.19981678692619,
          "lng": -149.90688040177855,
          "placeId": "ChIJjXJ229mXyFYRN9Bs-plBkds"
        },
        {
          "lat": 61.199810717406486,
          "lng": -149.9068665328672,
          "placeId": "ChIJjXJ229mXyFYRN9Bs-plBkds"
        },
        {
          "lat": 61.199804647884726,
          "lng": -149.90685266395977,
          "placeId": "ChIJjXJ229mXyFYRN9Bs-plBkds"
        },
        {
          "lat": 61.199798818132386,
          "lng": -149.90683934293546,
          "placeId": "ChIJjXJ229mXyFYRN9Bs-plBkds"
        },
        {
          "lat": 61.19979274860661,
          "lng": -149.90682547403563,
          "placeId": "ChIJjXJ229mXyFYRN9Bs-plBkds"
        },
        {
          "lat": 61.19978667907877,
          "lng": -149.90681160513972,
          "placeId": "ChIJjXJ229mXyFYRN9Bs-plBkds"
        },
        {
          "lat": 61.19978060954891,
          "lng": -149.9067977362477,
          "placeId": "ChIJjXJ229mXyFYRN9Bs-plBkds"
        },
        {
          "lat": 61.19977408789536,
          "lng": -149.9067828342615,
          "placeId": "ChIJjXJ229mXyFYRN9Bs-plBkds"
        },
        {
          "lat": 61.1997680183612,
          "lng": -149.9067689653775,
          "placeId": "ChIJjXJ229mXyFYRN9Bs-plBkds"
        },
        {
          "lat": 61.19976218859678,
          "lng": -149.90675564437535,
          "placeId": "ChIJjXJ229mXyFYRN9Bs-plBkds"
        },
        {
          "lat": 61.19975611905858,
          "lng": -149.90674177549894,
          "placeId": "ChIJjXJ229mXyFYRN9Bs-plBkds"
        },
        {
          "lat": 61.199750049518336,
          "lng": -149.90672790662646,
          "placeId": "ChIJjXJ229mXyFYRN9Bs-plBkds"
        },
        {
          "lat": 61.199743979976056,
          "lng": -149.9067140377579,
          "placeId": "ChIJjXJ229mXyFYRN9Bs-plBkds"
        },
        {
          "lat": 61.19973791043173,
          "lng": -149.90670016889322,
          "placeId": "ChIJjXJ229mXyFYRN9Bs-plBkds"
        },
        {
          "lat": 61.199731840885356,
          "lng": -149.90668630003248,
          "placeId": "ChIJjXJ229mXyFYRN9Bs-plBkds"
        },
        {
          "lat": 61.199726011109064,
          "lng": -149.90667297905236,
          "placeId": "ChIJjXJ229mXyFYRN9Bs-plBkds"
        },
        {
          "lat": 61.199719941558655,
          "lng": -149.9066591101992,
          "placeId": "ChIJjXJ229mXyFYRN9Bs-plBkds"
        },
        {
          "lat": 61.19971387200621,
          "lng": -149.90664524135002,
          "placeId": "ChIJjXJ229mXyFYRN9Bs-plBkds"
        },
        {
          "lat": 61.19970780245172,
          "lng": -149.9066313725047,
          "placeId": "ChIJjXJ229mXyFYRN9Bs-plBkds"
        },
        {
          "lat": 61.1997017328952,
          "lng": -149.90661750366334,
          "placeId": "ChIJjXJ229mXyFYRN9Bs-plBkds"
        }
      ]
    },
    {
      "startLocation": {
        "lat": 61.1997016,
        "lng": -149.9066172
      },
      "endLocation": {
        "lat": 61.1996204,
        "lng": -149.9064491
      },
      "distance": 13,
      "duration": 1,
      "points": [
        {
          "lat": 61.1997016,
          "lng": -149.9066172,
          "placeId": "ChIJl_my6NmXyFYRcFzQcMV8Uvs"
        },
        {
          "lat": 61.19969511343167,
          "lng": -149.90660376404858,
          "placeId": "ChIJl_my6NmXyFYRcFzQcMV8Uvs"
        },
        {
          "lat": 61.199688975670945,
          "lng": -149.90659105060735,
          "placeId": "ChIJl_my6NmXyFYRcFzQcMV8Uvs"
        },
        {
          "lat": 61.19968283790847,
          "lng": -149.90657833716986,
          "placeId": "ChIJl_my6NmXyFYRcFzQcMV8Uvs"
        },
        {
          "lat": 61.19967670014422,
          "lng": -149.90656562373616,
          "placeId": "ChIJl_my6NmXyFYRcFzQcMV8Uvs"
        },
        {
          "lat": 61.199670302199976,
          "lng": -149.90655237138753,
          "placeId": "ChIJl_my6NmXyFYRcFzQcMV8Uvs"
        },
        {
          "lat": 61.19966416443206,
          "lng": -149.90653965796142,
          "placeId": "ChIJl_my6NmXyFYRcFzQcMV8Uvs"
        },
        {
          "lat": 61.19965802666238,
          "lng": -149.90652694453902,
          "placeId": "ChIJl_my6NmXyFYRcFzQcMV8Uvs"
        },
        {
          "lat": 61.19965188889093,
          "lng": -149.9065142311204,
          "placeId": "ChIJl_my6NmXyFYRcFzQcMV8Uvs"
        },
        {
          "lat": 61.19964525005988,
          "lng": -149.9065004798448,
          "placeId": "ChIJl_my6NmXyFYRcFzQcMV8Uvs"
        },
        {
          "lat": 61.199639112284736,
          "lng": -149.9064877664339,
          "placeId": "ChIJl_my6NmXyFYRcFzQcMV8Uvs"
        },
        {
          "lat": 61.199632974507814,
          "lng": -149.90647505302687,
          "placeId": "ChIJl_my6NmXyFYRcFzQcMV8Uvs"
        },
        {
          "lat": 61.19962683672915,
          "lng": -149.9064623396236,
          "placeId": "ChIJl_my6NmXyFYRcFzQcMV8Uvs"
        },
        {
          "lat": 61.19962019789009,
          "lng": -149.9064485883641,
          "placeId": "ChIJl_my6NmXyFYRcFzQcMV8Uvs"
        }
      ]
    },
    {
      "startLocation": {
        "lat": 61.1996204,
        "lng": -149.9064491
      },
      "endLocation": {
        "lat": 61.1995777,
        "lng": -149.906365
      },
      "distance": 7,
      "duration": 1,
      "points": [
        {
          "lat": 61.19962019789009,
          "lng": -149.9064485883641,
          "placeId": "ChIJl_my6NmXyFYRcFzQcMV8Uvs"
        },
        {
          "lat": 61.19961422508865,
          "lng": -149.90643651681222,
          "placeId": "ChIJl_my6NmXyFYRcFzQcMV8Uvs"
        },
        {
          "lat": 61.199608235396404,
          "lng": -149.90642449468496,
          "placeId": "ChIJl_my6NmXyFYRcFzQcMV8Uvs"
        },
        {
          "lat": 61.19960224570253,
          "lng": -149.9064124725611,
          "placeId": "ChIJl_my6NmXyFYRcFzQcMV8Uvs"
        },
        {
          "lat": 61.19959625600706,
          "lng": -149.90640045044074,
          "placeId": "ChIJl_my6NmXyFYRcFzQcMV8Uvs"
        },
        {
          "lat": 61.19959026630996,
          "lng": -149.90638842832385,
          "placeId": "ChIJl_my6NmXyFYRcFzQcMV8Uvs"
        },
        {
          "lat": 61.19958427661124,
          "lng": -149.90637640621043,
          "placeId": "ChIJl_my6NmXyFYRcFzQcMV8Uvs"
        },
        {
          "lat": 61.19957828691091,
          "lng": -149.90636438410047,
          "placeId": "ChIJl_my6NmXyFYRcFzQcMV8Uvs"
        }
      ]
    },
    {
      "startLocation": {
        "lat": 61.1995777,
        "lng": -149.906365
      },
      "endLocation": {
        "lat": 61.19952059999999,
        "lng": -149.9062486
      },
      "distance": 9,
      "duration": 1,
      "points": [
        {
          "lat": 61.19957828691091,
          "lng": -149.90636438410047,
          "placeId": "ChIJl_my6NmXyFYRcFzQcMV8Uvs"
        },
        {
          "lat": 61.199571539669336,
          "lng": -149.9063508415144,
          "placeId": "ChIJl_my6NmXyFYRcFzQcMV8Uvs"
        },
        {
          "lat": 61.199565309221306,
          "lng": -149.90633833620743,
          "placeId": "ChIJl_my6NmXyFYRcFzQcMV8Uvs"
        },
        {
          "lat": 61.199559078771586,
          "lng": -149.90632583090428,
          "placeId": "ChIJl_my6NmXyFYRcFzQcMV8Uvs"
        },
        {
          "lat": 61.19955233152412,
          "lng": -149.90631228833064,
          "placeId": "ChIJl_my6NmXyFYRcFzQcMV8Uvs"
        },
        {
          "lat": 61.199546101070794,
          "lng": -149.90629978303537,
          "placeId": "ChIJl_my6NmXyFYRcFzQcMV8Uvs"
        },
        {
          "lat": 61.19953987061577,
          "lng": -149.90628727774396,
          "placeId": "ChIJl_my6NmXyFYRcFzQcMV8Uvs"
        },
        {
          "lat": 61.199533123362414,
          "lng": -149.90627373518276,
          "placeId": "ChIJl_my6NmXyFYRcFzQcMV8Uvs"
        },
        {
          "lat": 61.1995271336483,
          "lng": -149.9062617131024,
          "placeId": "ChIJl_my6NmXyFYRcFzQcMV8Uvs"
        },
        {
          "lat": 61.199520903188024,
          "lng": -149.90624920782255,
          "placeId": "ChIJl_my6NmXyFYRcFzQcMV8Uvs"
        }
      ]
    },
    {
      "startLocation": {
        "lat": 61.19952059999999,
        "lng": -149.9062486
      },
      "endLocation": {
        "lat": 61.19942839999999,
        "lng": -149.9060966
      },
      "distance": 13,
      "duration": 1,
      "points": [
        {
          "lat": 61.199520903188024,
          "lng": -149.90624920782255,
          "placeId": "ChIJl_my6NmXyFYRcFzQcMV8Uvs"
        },
        {
          "lat": 61.199513823585406,
          "lng": -149.90623746095304,
          "placeId": "ChIJl_my6NmXyFYRcFzQcMV8Uvs"
        },
        {
          "lat": 61.19950610322895,
          "lng": -149.9062247302734,
          "placeId": "ChIJl_my6NmXyFYRcFzQcMV8Uvs"
        },
        {
          "lat": 61.19949923059608,
          "lng": -149.90621339747622,
          "placeId": "ChIJl_my6NmXyFYRcFzQcMV8Uvs"
        },
        {
          "lat": 61.19949212332289,
          "lng": -149.90620167776999,
          "placeId": "ChIJl_my6NmXyFYRcFzQcMV8Uvs"
        },
        {
          "lat": 61.199485016048094,
          "lng": -149.906189958068,
          "placeId": "ChIJl_my6NmXyFYRcFzQcMV8Uvs"
        },
        {
          "lat": 61.19947790877168,
          "lng": -149.90617823837033,
          "placeId": "ChIJl_my6NmXyFYRcFzQcMV8Uvs"
        },
        {
          "lat": 61.19947103613251,
          "lng": -149.90616690558946,
          "placeId": "ChIJl_my6NmXyFYRcFzQcMV8Uvs"
        },
        {
          "lat": 61.1994639288529,
          "lng": -149.9061551859002,
          "placeId": "ChIJl_my6NmXyFYRcFzQcMV8Uvs"
        },
        {
          "lat": 61.19945682157166,
          "lng": -149.9061434662152,
          "placeId": "ChIJl_my6NmXyFYRcFzQcMV8Uvs"
        },
        {
          "lat": 61.199449948927786,
          "lng": -149.90613213344656,
          "placeId": "ChIJl_my6NmXyFYRcFzQcMV8Uvs"
        },
        {
          "lat": 61.199442841643375,
          "lng": -149.90612041377003,
          "placeId": "ChIJl_my6NmXyFYRcFzQcMV8Uvs"
        },
        {
          "lat": 61.19943512126897,
          "lng": -149.9061076831363,
          "placeId": "ChIJl_my6NmXyFYRcFzQcMV8Uvs"
        },
        {
          "lat": 61.19942839999999,
          "lng": -149.90609659999998,
          "placeId": "ChIJl_my6NmXyFYRcFzQcMV8Uvs"
        }
      ]
    },
    {
      "startLocation": {
        "lat": 61.19942839999999,
        "lng": -149.9060966
      },
      "endLocation": {
        "lat": 61.1994008,
        "lng": -149.9060571
      },
      "distance": 4,
      "duration": 1,
      "points": [
        {
          "lat": 61.19942822019175,
          "lng": -149.90609634110288,
          "placeId": "ChIJlc0f8tmXyFYRQh-fvkjtpTA"
        },
        {
          "lat": 61.19942123800558,
          "lng": -149.9060862877971,
          "placeId": "ChIJlc0f8tmXyFYRQh-fvkjtpTA"
        },
        {
          "lat": 61.19941493095913,
          "lng": -149.9060772065965,
          "placeId": "ChIJlc0f8tmXyFYRQh-fvkjtpTA"
        },
        {
          "lat": 61.199407948770585,
          "lng": -149.90606715329787,
          "placeId": "ChIJlc0f8tmXyFYRQh-fvkjtpTA"
        },
        {
          "lat": 61.199400915918645,
          "lng": -149.9060573302762,
          "placeId": "ChIJlc0f8tmXyFYRQh-fvkjtpTA"
        }
      ]
    },
    {
      "startLocation": {
        "lat": 61.1994008,
        "lng": -149.9060571
      },
      "endLocation": {
        "lat": 61.199352,
        "lng": -149.9060022
      },
      "distance": 6,
      "duration": 1,
      "points": [
        {
          "lat": 61.199400915918645,
          "lng": -149.9060573302762,
          "placeId": "ChIJlc0f8tmXyFYRQh-fvkjtpTA"
        },
        {
          "lat": 61.19939287113596,
          "lng": -149.90604850618516,
          "placeId": "ChIJlc0f8tmXyFYRQh-fvkjtpTA"
        },
        {
          "lat": 61.199384826352244,
          "lng": -149.90603968209808,
          "placeId": "ChIJlc0f8tmXyFYRQh-fvkjtpTA"
        },
        {
          "lat": 61.19937599985326,
          "lng": -149.9060300005764,
          "placeId": "ChIJlc0f8tmXyFYRQh-fvkjtpTA"
        },
        {
          "lat": 61.1993677560595,
          "lng": -149.90602095821217,
          "placeId": "ChIJlc0f8tmXyFYRQh-fvkjtpTA"
        },
        {
          "lat": 61.19935971127261,
          "lng": -149.90601213413765,
          "placeId": "ChIJlc0f8tmXyFYRQh-fvkjtpTA"
        },
        {
          "lat": 61.19935166648472,
          "lng": -149.90600331006718,
          "placeId": "ChIJlc0f8tmXyFYRQh-fvkjtpTA"
        }
      ]
    },
    {
      "startLocation": {
        "lat": 61.199352,
        "lng": -149.9060022
      },
      "endLocation": {
        "lat": 61.1992595,
        "lng": -149.905902
      },
      "distance": 12,
      "duration": 2,
      "points": [
        {
          "lat": 61.19935166648472,
          "lng": -149.90600331006718,
          "placeId": "ChIJlc0f8tmXyFYRQh-fvkjtpTA"
        },
        {
          "lat": 61.199343820703746,
          "lng": -149.90599470428597,
          "placeId": "ChIJlc0f8tmXyFYRQh-fvkjtpTA"
        },
        {
          "lat": 61.199336557628655,
          "lng": -149.9059867376602,
          "placeId": "ChIJlc0f8tmXyFYRQh-fvkjtpTA"
        },
        {
          "lat": 61.19932871184583,
          "lng": -149.90597813188637,
          "placeId": "ChIJlc0f8tmXyFYRQh-fvkjtpTA"
        },
        {
          "lat": 61.19932086606199,
          "lng": -149.9059695261163,
          "placeId": "ChIJlc0f8tmXyFYRQh-fvkjtpTA"
        },
        {
          "lat": 61.19931282126917,
          "lng": -149.90596070206522,
          "placeId": "ChIJlc0f8tmXyFYRQh-fvkjtpTA"
        },
        {
          "lat": 61.199305757198594,
          "lng": -149.90595295373825,
          "placeId": "ChIJlc0f8tmXyFYRQh-fvkjtpTA"
        },
        {
          "lat": 61.19929791141189,
          "lng": -149.90594434797933,
          "placeId": "ChIJlc0f8tmXyFYRQh-fvkjtpTA"
        },
        {
          "lat": 61.19928986661615,
          "lng": -149.9059355239397,
          "placeId": "ChIJlc0f8tmXyFYRQh-fvkjtpTA"
        },
        {
          "lat": 61.19928280254304,
          "lng": -149.90592777562276,
          "placeId": "ChIJlc0f8tmXyFYRQh-fvkjtpTA"
        },
        {
          "lat": 61.19927495675347,
          "lng": -149.905919169875,
          "placeId": "ChIJlc0f8tmXyFYRQh-fvkjtpTA"
        },
        {
          "lat": 61.1992669119548,
          "lng": -149.90591034584685,
          "placeId": "ChIJlc0f8tmXyFYRQh-fvkjtpTA"
        },
        {
          "lat": 61.19925986042997,
          "lng": -149.90590252016545,
          "placeId": "ChIJlc0f8tmXyFYRQh-fvkjtpTA"
        }
      ]
    },
    {
      "startLocation": {
        "lat": 61.1992595,
        "lng": -149.905902
      },
      "endLocation": {
        "lat": 61.1992108,
        "lng": -149.9058463
      },
      "distance": 6,
      "duration": 1,
      "points": [
        {
          "lat": 61.19925986042997,
          "lng": -149.90590252016545,
          "placeId": "ChIJlc0f8tmXyFYRQh-fvkjtpTA"
        },
        {
          "lat": 61.199251148068576,
          "lng": -149.90589244816113,
          "placeId": "ChIJlc0f8tmXyFYRQh-fvkjtpTA"
        },
        {
          "lat": 61.19924299415962,
          "lng": -149.90588302176664,
          "placeId": "ChIJlc0f8tmXyFYRQh-fvkjtpTA"
        },
        {
          "lat": 61.199235045042826,
          "lng": -149.90587383212926,
          "placeId": "ChIJlc0f8tmXyFYRQh-fvkjtpTA"
        },
        {
          "lat": 61.199227095924925,
          "lng": -149.90586464249597,
          "placeId": "ChIJlc0f8tmXyFYRQh-fvkjtpTA"
        },
        {
          "lat": 61.19921914680593,
          "lng": -149.90585545286675,
          "placeId": "ChIJlc0f8tmXyFYRQh-fvkjtpTA"
        },
        {
          "lat": 61.19921092171288,
          "lng": -149.9058463674016,
          "placeId": "ChIJlc0f8tmXyFYRQh-fvkjtpTA"
        }
      ]
    },
    {
      "startLocation": {
        "lat": 61.1992108,
        "lng": -149.9058463
      },
      "endLocation": {
        "lat": 61.19917019999999,
        "lng": -149.9058091
      },
      "distance": 5,
      "duration": 1,
      "points": [
        {
          "lat": 61.19921092171288,
          "lng": -149.9058463674016,
          "placeId": "ChIJlc0f8tmXyFYRQh-fvkjtpTA"
        },
        {
          "lat": 61.19920298312464,
          "lng": -149.9058390791961,
          "placeId": "ChIJlc0f8tmXyFYRQh-fvkjtpTA"
        },
        {
          "lat": 61.19919486631672,
          "lng": -149.90583162737605,
          "placeId": "ChIJlc0f8tmXyFYRQh-fvkjtpTA"
        },
        {
          "lat": 61.199186091344856,
          "lng": -149.90582357131836,
          "placeId": "ChIJlc0f8tmXyFYRQh-fvkjtpTA"
        },
        {
          "lat": 61.199178152754364,
          "lng": -149.90581628312341,
          "placeId": "ChIJlc0f8tmXyFYRQh-fvkjtpTA"
        },
        {
          "lat": 61.19917000610716,
          "lng": -149.90580896635282,
          "placeId": "ChIJlc0f8tmXyFYRQh-fvkjtpTA"
        }
      ]
    },
    {
      "startLocation": {
        "lat": 61.19917019999999,
        "lng": -149.9058091
      },
      "endLocation": {
        "lat": 61.19905960000001,
        "lng": -149.9057227
      },
      "distance": 13,
      "duration": 2,
      "points": [
        {
          "lat": 61.19917000610716,
          "lng": -149.90580896635282,
          "placeId": "ChIJlc0f8tmXyFYRQh-fvkjtpTA"
        },
        {
          "lat": 61.19916188787628,
          "lng": -149.90580261774204,
          "placeId": "ChIJlc0f8tmXyFYRQh-fvkjtpTA"
        },
        {
          "lat": 61.19915305288767,
          "lng": -149.9057957086171,
          "placeId": "ChIJlc0f8tmXyFYRQh-fvkjtpTA"
        },
        {
          "lat": 61.19914493465562,
          "lng": -149.90578936001273,
          "placeId": "ChIJlc0f8tmXyFYRQh-fvkjtpTA"
        },
        {
          "lat": 61.19913609966575,
          "lng": -149.90578245089478,
          "placeId": "ChIJlc0f8tmXyFYRQh-fvkjtpTA"
        },
        {
          "lat": 61.19912798143254,
          "lng": -149.9057761022968,
          "placeId": "ChIJlc0f8tmXyFYRQh-fvkjtpTA"
        },
        {
          "lat": 61.1991189874964,
          "lng": -149.9057690688882,
          "placeId": "ChIJlc0f8tmXyFYRQh-fvkjtpTA"
        },
        {
          "lat": 61.199111028207035,
          "lng": -149.90576284459428,
          "placeId": "ChIJlc0f8tmXyFYRQh-fvkjtpTA"
        },
        {
          "lat": 61.19910203426959,
          "lng": -149.9057558111928,
          "placeId": "ChIJlc0f8tmXyFYRQh-fvkjtpTA"
        },
        {
          "lat": 61.19909391603407,
          "lng": -149.9057494626077,
          "placeId": "ChIJlc0f8tmXyFYRQh-fvkjtpTA"
        },
        {
          "lat": 61.19908508104034,
          "lng": -149.90574255351072,
          "placeId": "ChIJlc0f8tmXyFYRQh-fvkjtpTA"
        },
        {
          "lat": 61.199076962803666,
          "lng": -149.90573620493205,
          "placeId": "ChIJlc0f8tmXyFYRQh-fvkjtpTA"
        },
        {
          "lat": 61.19906796886366,
          "lng": -149.9057291715448,
          "placeId": "ChIJlc0f8tmXyFYRQh-fvkjtpTA"
        },
        {
          "lat": 61.19905999588791,
          "lng": -149.90572302524868,
          "placeId": "ChIJlc0f8tmXyFYRQh-fvkjtpTA"
        }
      ]
    },
    {
      "startLocation": {
        "lat": 61.19905960000001,
        "lng": -149.9057227
      },
      "endLocation": {
        "lat": 61.1989999,
        "lng": -149.9056809
      },
      "distance": 7,
      "duration": 1,
      "points": [
        {
          "lat": 61.19905999588791,
          "lng": -149.90572302524868,
          "placeId": "ChIJlc0f8tmXyFYRQh-fvkjtpTA"
        },
        {
          "lat": 61.19905104196715,
          "lng": -149.9057167423179,
          "placeId": "ChIJlc0f8tmXyFYRQh-fvkjtpTA"
        },
        {
          "lat": 61.19904298548558,
          "lng": -149.9057110891199,
          "placeId": "ChIJlc0f8tmXyFYRQh-fvkjtpTA"
        },
        {
          "lat": 61.19903403156377,
          "lng": -149.9057048061956,
          "placeId": "ChIJlc0f8tmXyFYRQh-fvkjtpTA"
        },
        {
          "lat": 61.199025077641394,
          "lng": -149.90569852327462,
          "placeId": "ChIJlc0f8tmXyFYRQh-fvkjtpTA"
        },
        {
          "lat": 61.199017021158404,
          "lng": -149.9056928700855,
          "placeId": "ChIJlc0f8tmXyFYRQh-fvkjtpTA"
        },
        {
          "lat": 61.199008067234985,
          "lng": -149.90568658717098,
          "placeId": "ChIJlc0f8tmXyFYRQh-fvkjtpTA"
        },
        {
          "lat": 61.19899999488256,
          "lng": -149.90568103397766,
          "placeId": "ChIJlc0f8tmXyFYRQh-fvkjtpTA"
        }
      ]
    },
    {
      "startLocation": {
        "lat": 61.1989999,
        "lng": -149.9056809
      },
      "endLocation": {
        "lat": 61.1988745,
        "lng": -149.9055996
      },
      "distance": 15,
      "duration": 2,
      "points": [
        {
          "lat": 61.19899999488256,
          "lng": -149.90568103397766,
          "placeId": "ChIJlc0f8tmXyFYRQh-fvkjtpTA"
        },
        {
          "lat": 61.19899188391891,
          "lng": -149.90567577073023,
          "placeId": "ChIJlc0f8tmXyFYRQh-fvkjtpTA"
        },
        {
          "lat": 61.19898299918894,
          "lng": -149.90567000538502,
          "placeId": "ChIJlc0f8tmXyFYRQh-fvkjtpTA"
        },
        {
          "lat": 61.198975025427124,
          "lng": -149.90566483117445,
          "placeId": "ChIJlc0f8tmXyFYRQh-fvkjtpTA"
        },
        {
          "lat": 61.19896600349363,
          "lng": -149.9056589768038,
          "placeId": "ChIJlc0f8tmXyFYRQh-fvkjtpTA"
        },
        {
          "lat": 61.198958029730996,
          "lng": -149.90565380259855,
          "placeId": "ChIJlc0f8tmXyFYRQh-fvkjtpTA"
        },
        {
          "lat": 61.19894991876533,
          "lng": -149.90564853936456,
          "placeId": "ChIJlc0f8tmXyFYRQh-fvkjtpTA"
        },
        {
          "lat": 61.19894103403314,
          "lng": -149.90564277403402,
          "placeId": "ChIJlc0f8tmXyFYRQh-fvkjtpTA"
        },
        {
          "lat": 61.198933060269326,
          "lng": -149.9056375998366,
          "placeId": "ChIJlc0f8tmXyFYRQh-fvkjtpTA"
        },
        {
          "lat": 61.19892494930247,
          "lng": -149.9056323366106,
          "placeId": "ChIJlc0f8tmXyFYRQh-fvkjtpTA"
        },
        {
          "lat": 61.19891606456898,
          "lng": -149.90562657128882,
          "placeId": "ChIJlc0f8tmXyFYRQh-fvkjtpTA"
        },
        {
          "lat": 61.1989079536013,
          "lng": -149.90562130806822,
          "placeId": "ChIJlc0f8tmXyFYRQh-fvkjtpTA"
        },
        {
          "lat": 61.19889997983592,
          "lng": -149.90561613388118,
          "placeId": "ChIJlc0f8tmXyFYRQh-fvkjtpTA"
        },
        {
          "lat": 61.1988909578984,
          "lng": -149.9056102795372,
          "placeId": "ChIJlc0f8tmXyFYRQh-fvkjtpTA"
        },
        {
          "lat": 61.19888298413223,
          "lng": -149.9056051053555,
          "placeId": "ChIJlc0f8tmXyFYRQh-fvkjtpTA"
        },
        {
          "lat": 61.19887501036566,
          "lng": -149.90559993117634,
          "placeId": "ChIJlc0f8tmXyFYRQh-fvkjtpTA"
        }
      ]
    },
    {
      "startLocation": {
        "lat": 61.1988745,
        "lng": -149.9055996
      },
      "endLocation": {
        "lat": 61.19891259999999,
        "lng": -149.9053949
      },
      "distance": 12,
      "duration": 1,
      "points": [
        {
          "lat": 61.19887450015507,
          "lng": -149.90559959916686,
          "placeId": "ChIJV7XB89mXyFYRwgBkXnyRXKM"
        },
        {
          "lat": 61.19887764299321,
          "lng": -149.90558271371114,
          "placeId": "ChIJV7XB89mXyFYRwgBkXnyRXKM"
        },
        {
          "lat": 61.198880947782875,
          "lng": -149.90556495812635,
          "placeId": "ChIJV7XB89mXyFYRwgBkXnyRXKM"
        },
        {
          "lat": 61.19888409061622,
          "lng": -149.9055480726664,
          "placeId": "ChIJV7XB89mXyFYRwgBkXnyRXKM"
        },
        {
          "lat": 61.198887233447216,
          "lng": -149.90553118720433,
          "placeId": "ChIJV7XB89mXyFYRwgBkXnyRXKM"
        },
        {
          "lat": 61.19889037627586,
          "lng": -149.90551430174025,
          "placeId": "ChIJV7XB89mXyFYRwgBkXnyRXKM"
        },
        {
          "lat": 61.19889364897451,
          "lng": -149.90549671850854,
          "placeId": "ChIJV7XB89mXyFYRwgBkXnyRXKM"
        },
        {
          "lat": 61.19889679179828,
          "lng": -149.90547983304072,
          "placeId": "ChIJV7XB89mXyFYRwgBkXnyRXKM"
        },
        {
          "lat": 61.19889993461972,
          "lng": -149.90546294757087,
          "placeId": "ChIJV7XB89mXyFYRwgBkXnyRXKM"
        },
        {
          "lat": 61.19890307743879,
          "lng": -149.90544606209897,
          "placeId": "ChIJV7XB89mXyFYRwgBkXnyRXKM"
        },
        {
          "lat": 61.19890622025552,
          "lng": -149.905429176625,
          "placeId": "ChIJV7XB89mXyFYRwgBkXnyRXKM"
        },
        {
          "lat": 61.19890936306991,
          "lng": -149.90541229114905,
          "placeId": "ChIJV7XB89mXyFYRwgBkXnyRXKM"
        },
        {
          "lat": 61.19891259999999,
          "lng": -149.9053949,
          "placeId": "ChIJV7XB89mXyFYRwgBkXnyRXKM"
        }
      ]
    },
    {
      "startLocation": {
        "lat": 61.19891259999999,
        "lng": -149.9053949
      },
      "endLocation": {
        "lat": 61.1989125,
        "lng": -149.90534
      },
      "distance": 3,
      "duration": 0,
      "points": [
        {
          "lat": 61.19891259999999,
          "lng": -149.9053949,
          "placeId": "ChIJPwjp89mXyFYRctQOXm4JkYM"
        },
        {
          "lat": 61.19891256206049,
          "lng": -149.9053770040002,
          "placeId": "ChIJPwjp89mXyFYRctQOXm4JkYM"
        },
        {
          "lat": 61.19891252177873,
          "lng": -149.90535800436842,
          "placeId": "ChIJPwjp89mXyFYRctQOXm4JkYM"
        },
        {
          "lat": 61.19891248361459,
          "lng": -149.90534000471737,
          "placeId": "ChIJPwjp89mXyFYRctQOXm4JkYM"
        }
      ]
    }
  ]
}